redis_caching/__init__.py
redis_caching/caching.py
redis_caching-1.0.1.dist-info/METADATA
redis_caching-1.0.1.dist-info/WHEEL
redis_caching-1.0.1.dist-info/top_level.txt
redis_caching-1.0.1.dist-info/RECORD
