Metadata-Version: 2.1
Name: redis-caching
Version: 1.0.1
Summary: Redis Caching is a Python library that provides caching functionalities using Redis for storing and retrieving cached values.
Author: Maksymilian Sawicz
